energymon/__init__.py
energymon/context.py
energymon/util.py
energymon-0.1.2.dist-info/LICENSE-APACHE
energymon-0.1.2.dist-info/LICENSE-MIT
energymon-0.1.2.dist-info/METADATA
energymon-0.1.2.dist-info/WHEEL
energymon-0.1.2.dist-info/top_level.txt
energymon-0.1.2.dist-info/RECORD
