Metadata-Version: 2.1
Name: energymon
Version: 0.1.2
Summary: Python bindings to native energymon libraries
Home-page: https://github.com/energymon/energymon-py
Author: Connor Imes
Keywords: energymon,energy,monitoring,bindings
Classifier: Topic :: System :: Monitoring
Classifier: Topic :: Utilities
Requires-Python: >=3.6
License-File: LICENSE-MIT
License-File: LICENSE-APACHE
